fakespotipy/__init__.py
fakespotipy-0.8.0.dist-info/METADATA
fakespotipy-0.8.0.dist-info/RECORD
fakespotipy-0.8.0.dist-info/WHEEL
fakespotipy-0.8.0.dist-info/top_level.txt
