Metadata-Version: 2.1
Name: fakespotipy
Version: 0.8.0
Summary: A fake spotipy client. For unit tests and stuff.
Home-page: https://github.com/rcrdclub/fakespotipy
Author: @LoisaidaSam
Author-email: sam.sandberg@gmail.com
License: MIT
Keywords: spotify,spotipy,wrapper,testing,unit testing
Platform: UNKNOWN
